ruSpamLib/__init__.py
ruSpamLib/detector.py
ruSpam-0.3.5.dist-info/LICENSE
ruSpam-0.3.5.dist-info/METADATA
ruSpam-0.3.5.dist-info/WHEEL
ruSpam-0.3.5.dist-info/top_level.txt
ruSpam-0.3.5.dist-info/RECORD
