Metadata-Version: 2.1
Name: ruSpam
Version: 0.3.5
Summary: A simple spam detection library using a pre-trained model from Hugging Face
Author: NeuroSpaceX
Author-email: totoshkus@gmail.com
Classifier: Programming Language :: Python :: 3
Classifier: License :: OSI Approved :: MIT License
Classifier: Operating System :: OS Independent
Requires-Python: >=3.6
License-File: LICENSE
Requires-Dist: requests
